{
  "name": "Kyle Triplett",
  "url": "https://www.nypl.org/blog/author/1082",
  "number": 1082,
  "posts": [
    {
      "title": "Total Eclipse of the Art: Trouvelot and the 1878 Eclipse",
      "date": "August 17, 2017",
      "timestamp": 1502942400,
      "text": "For Americans in the post-Civil War years, the most iconic images of the cosmos were largely the work of one man: \u00c9tienne Leopold Trouvelot (1827-1895), an artist and amateur astronomer who produced incredible images of the heavens.",
      "url": "https://www.nypl.org/blog/2017/08/17/total-eclipse-of-the-art",
      "archive": "https://web.archive.org/web/20210312065229/https://www.nypl.org/blog/2017/08/17/total-eclipse-of-the-art",
      "oldestArchive": "https://web.archive.org/web/20200717093432/https://www.nypl.org/blog/2017/08/17/total-eclipse-of-the-art"
    },
    {
      "title": "The Curious Shape of Money in Old New York",
      "date": "August 8, 2017",
      "timestamp": 1502164800,
      "text": "On August 8, we're celebrating National Dollar Day, which commemorates the day that Congress defined the construction of the dollar, the newly established currency of the United States.",
      "url": "https://www.nypl.org/blog/2017/08/08/curious-shape-money-old-new-york",
      "archive": "https://web.archive.org/web/20211225031003/https://www.nypl.org/blog/2017/08/08/curious-shape-money-old-new-york",
      "oldestArchive": "https://web.archive.org/web/20211225031003/https://www.nypl.org/blog/2017/08/08/curious-shape-money-old-new-york"
    },
    {
      "title": "Rare Books: Machinae Novae of 1595",
      "date": "May 18, 2012",
      "timestamp": 1337313600,
      "text": "",
      "url": "https://www.nypl.org/blog/2012/05/18/rare-books-machinae-novae",
      "archive": "https://web.archive.org/web/20210315040023/https://www.nypl.org/blog/2012/05/18/rare-books-machinae-novae",
      "oldestArchive": "https://web.archive.org/web/20120520223741/http://www.nypl.org:80/blog/2012/05/18/rare-books-machinae-novae"
    }
  ]
}