{
  "name": "Lauren Weiss",
  "url": "https://www.nypl.org/blog/author/2552",
  "number": 2552,
  "posts": [
    {
      "title": "Quiz: Which Oversized Kid-Lit Animal Are You?",
      "date": "September 13, 2017",
      "timestamp": 1505275200,
      "text": "Find out which beloved kid-lit beast matches your personality!",
      "url": "https://www.nypl.org/blog/2017/09/13/quiz-which-oversized-kid-lit-animal-are-you",
      "archive": "https://web.archive.org/web/20211224215004/https://www.nypl.org/blog/2017/09/13/quiz-which-oversized-kid-lit-animal-are-you",
      "oldestArchive": "https://web.archive.org/web/20211224215004/https://www.nypl.org/blog/2017/09/13/quiz-which-oversized-kid-lit-animal-are-you"
    },
    {
      "title": "Famed Documentarian Frederick Wiseman Turns His Camera on NYPL in Ex Libris",
      "date": "September 6, 2017",
      "timestamp": 1504670400,
      "text": "Master documentarian Frederick Wiseman, known for his spellbinding films about complex topics and institutions, turns his attention to The New York Public Library for his latest film, Ex Libris - The New York Public Library.",
      "url": "https://www.nypl.org/blog/2017/09/06/frederick-wiseman-ex-libris",
      "archive": "https://web.archive.org/web/20211224215017/https://www.nypl.org/blog/2017/09/06/frederick-wiseman-ex-libris",
      "oldestArchive": "https://web.archive.org/web/20211224215017/https://www.nypl.org/blog/2017/09/06/frederick-wiseman-ex-libris"
    },
    {
      "title": "NYPL #FridayReads: The Semi-Pro Edition September 1, 2017",
      "date": "September 1, 2017",
      "timestamp": 1504238400,
      "text": "During the week, it can be tough to stay on top of everything. On Fridays, though, we suggest kicking back to catch up on all the delightful literary reading the internet has to offer.",
      "url": "https://www.nypl.org/blog/2017/09/01/friday-reads-semi-pro-edition",
      "archive": "https://web.archive.org/web/20211224215036/https://www.nypl.org/blog/2017/09/01/friday-reads-semi-pro-edition",
      "oldestArchive": "https://web.archive.org/web/20211224215036/https://www.nypl.org/blog/2017/09/01/friday-reads-semi-pro-edition"
    },
    {
      "title": "NYPL Events: What's Happening 9/4-9/18",
      "date": "September 1, 2017",
      "timestamp": 1504238400,
      "text": "Welcome to our biweekly update on events happening during the next two weeks at The New York Public Library. With 92 locations across New York City, a lot is happening at the Library.",
      "url": "https://www.nypl.org/blog/2017/09/04/nypl-events",
      "archive": "https://web.archive.org/web/20211224215204/https://www.nypl.org/blog/2017/09/04/nypl-events",
      "oldestArchive": "https://web.archive.org/web/20211224215204/https://www.nypl.org/blog/2017/09/04/nypl-events"
    },
    {
      "title": "All the Authors, Thinkers, and Artists Coming to LIVE from the NYPL This Year",
      "date": "August 30, 2017",
      "timestamp": 1504065600,
      "text": "The New York Public Library\u2019s premiere conversation series is back, and our fall lineup of guests ranges from luminary authors like Salman Rushdie and Tony Kushner to influential thinkers like Muhammad Yunus and Van Jones.",
      "url": "https://www.nypl.org/blog/2017/08/30/live-from-the-nypl-2017",
      "archive": "https://web.archive.org/web/20211224215335/https://www.nypl.org/blog/2017/08/30/live-from-the-nypl-2017",
      "oldestArchive": "https://web.archive.org/web/20211224215335/https://www.nypl.org/blog/2017/08/30/live-from-the-nypl-2017"
    },
    {
      "title": "Announcing Our Summer Reading Essay Contest Winners",
      "date": "August 29, 2017",
      "timestamp": 1503979200,
      "text": "Of the more than 150 essays received, four grand prize winners were chosen to take a bow on the field at Yankee Stadium, meet a player, and and stick around to watch the game with their families.",
      "url": "https://www.nypl.org/blog/2017/08/29/summer-reading-essay-contest-winners",
      "archive": "https://web.archive.org/web/20170831151913/https://www.nypl.org/blog/2017/08/29/summer-reading-essay-contest-winners",
      "oldestArchive": "https://web.archive.org/web/20170831151913/https://www.nypl.org/blog/2017/08/29/summer-reading-essay-contest-winners"
    },
    {
      "title": "Quiz: How Well Do You Know Your Historical Poems?",
      "date": "August 4, 2017",
      "timestamp": 1501819200,
      "text": "Can you guess the historical figure or event referenced in these poems? It's harder than you think!",
      "url": "https://www.nypl.org/blog/2017/08/04/quiz-how-well-do-you-know-your-historical-poems",
      "archive": "https://web.archive.org/web/20211224215821/https://www.nypl.org/blog/2017/08/04/quiz-how-well-do-you-know-your-historical-poems",
      "oldestArchive": "https://web.archive.org/web/20211224215820/https://www.nypl.org/blog/2017/08/04/quiz-how-well-do-you-know-your-historical-poems"
    },
    {
      "title": "Announcing the 2017 Young Lions Fiction Award Finalists",
      "date": "March 23, 2017",
      "timestamp": 1490241600,
      "text": "We're pleased to announce the finalists for the seventeenth annual Young Lions Fiction Award, honoring the works of five commanding, diverse, young authors. From high-concept premises, to the exploration of heartbreaking family dynamics, each of these debut novels exemplifies the power of the written word.",
      "url": "https://www.nypl.org/blog/2017/03/23/2017-young-lions-fiction-award-finalists",
      "archive": "https://web.archive.org/web/20210717110659/https://www.nypl.org/blog/2017/03/23/2017-young-lions-fiction-award-finalists",
      "oldestArchive": "https://web.archive.org/web/20170622235925/https://www.nypl.org/blog/2017/03/23/2017-young-lions-fiction-award-finalists"
    },
    {
      "title": "Disney Classics in the Digital Collections",
      "date": "March 17, 2017",
      "timestamp": 1489723200,
      "text": "While the illustrators each gave the stories their own artistic spin, we spotted some traces of the Disney characters we know and love in the past.",
      "url": "https://www.nypl.org/blog/2017/03/17/disney-classics-digital-collections",
      "archive": "https://web.archive.org/web/20211224215930/https://www.nypl.org/blog/2017/03/17/disney-classics-digital-collections",
      "oldestArchive": "https://web.archive.org/web/20211224215913/https://www.nypl.org/blog/2017/03/17/disney-classics-digital-collections"
    },
    {
      "title": "#LiteraryMarchMadness 2017: Which Book Will Win?",
      "date": "March 16, 2017",
      "timestamp": 1489636800,
      "text": "Welcome to our Fourth Annual Literary March Madness (#LiteraryMarchMadness)! This is a bracket-style tournament like the NCAA March Madness basketball tournament, but with a literary twist: our competition pits beloved books against each other and the winner is decided by you!",
      "url": "https://www.nypl.org/blog/2017/03/16/literarymarchmadness-2017",
      "archive": "https://web.archive.org/web/20170917011352/https://www.nypl.org/blog/2017/03/16/literarymarchmadness-2017",
      "oldestArchive": "https://web.archive.org/web/20170917011352/https://www.nypl.org/blog/2017/03/16/literarymarchmadness-2017"
    },
    {
      "title": "12 #LibraryShelfie Photos We Loved",
      "date": "January 25, 2017",
      "timestamp": 1485320400,
      "text": "On the fourth Wednesday of January each year, libraries and readers across social media share selfies with bookshelves and tag them #LibraryShelfie!",
      "url": "https://www.nypl.org/blog/2017/01/25/12-libraryshelfie-photos-we-loved",
      "archive": "https://web.archive.org/web/20211224220307/https://www.nypl.org/blog/2017/01/25/12-libraryshelfie-photos-we-loved",
      "oldestArchive": "https://web.archive.org/web/20211224220307/https://www.nypl.org/blog/2017/01/25/12-libraryshelfie-photos-we-loved"
    },
    {
      "title": "#ReadersUnite to Share the Books They're Reading",
      "date": "January 5, 2017",
      "timestamp": 1483592400,
      "text": "This week, readers and writers are celebrating reading by posting the books they're reading to social media, joined together with the hashtag #ReadersUnite.",
      "url": "https://www.nypl.org/blog/2017/01/05/readersunite",
      "archive": "https://web.archive.org/web/20180327113548/https://www.nypl.org/blog/2017/01/05/readersunite",
      "oldestArchive": "https://web.archive.org/web/20180327113548/https://www.nypl.org/blog/2017/01/05/readersunite"
    },
    {
      "title": "NYPL's Most Popular Checkouts of 2016",
      "date": "December 28, 2016",
      "timestamp": 1482901200,
      "text": "Over 25 million items are circulated through our network of libraries each year, and among those items there are both expected front-runners and a few interesting surprises every year. For your perusal, we've compiled lists of the top books checked out systemwide and in The Bronx, Manhattan, and Staten Island in 2016.",
      "url": "https://www.nypl.org/blog/2016/12/22/nypls-most-popular-checkouts-2016",
      "archive": "https://web.archive.org/web/20211224220435/https://www.nypl.org/blog/2016/12/22/nypls-most-popular-checkouts-2016",
      "oldestArchive": "https://web.archive.org/web/20211101035630/https://www.nypl.org/blog/2016/12/22/nypls-most-popular-checkouts-2016"
    },
    {
      "title": "World AIDS Day: A Look in Our Collections",
      "date": "December 1, 2016",
      "timestamp": 1480568400,
      "text": "World AIDS Day is held on December 1 each year and is an opportunity for people worldwide to unite in the fight against HIV, show their support for people living with HIV and to commemorate those who have died. World AIDS Day was the first ever global health day, held for the first time in 1988.",
      "url": "https://www.nypl.org/blog/2016/12/01/world-aids-day",
      "archive": "https://web.archive.org/web/20211224220824/https://www.nypl.org/blog/2016/12/01/world-aids-day",
      "oldestArchive": "https://web.archive.org/web/20211224220615/https://www.nypl.org/blog/2016/12/01/world-aids-day"
    },
    {
      "title": "#GivingTuesday: Dedicate a NYPL Bookplate",
      "date": "November 29, 2016",
      "timestamp": 1480395600,
      "text": "It's #GivingTuesday\u2014the time of year we give back to the causes we are most passionate about. Donate $50 or more today, and give your loved one the unique gift of having his or her name placed in a brand new book entering the Library's circulation across NYC!",
      "url": "https://www.nypl.org/blog/2016/11/28/giving-tuesday-nypl",
      "archive": "https://web.archive.org/web/20211224221318/https://www.nypl.org/blog/2016/11/28/giving-tuesday-nypl",
      "oldestArchive": "https://web.archive.org/web/20211224221318/https://www.nypl.org/blog/2016/11/28/giving-tuesday-nypl"
    },
    {
      "title": "What Eliza Hamilton Left Behind",
      "date": "November 8, 2016",
      "timestamp": 1478581200,
      "text": "By now everyone knows that Eliza Hamilton, the wife of Alexander Hamilton, burned her husband's love letters before she died--and November 9th will be the 162nd anniversary of her death on that day in 1854 at the age of 97. But if you're an astute historian, you might notice that Alexander Hamilton was killed in that famous duel way back in 1804.",
      "url": "https://www.nypl.org/blog/2016/11/08/what-eliza-hamilton-left-behind",
      "archive": "https://web.archive.org/web/20211224221728/https://www.nypl.org/blog/2016/11/08/what-eliza-hamilton-left-behind",
      "oldestArchive": "https://web.archive.org/web/20180216002237/https://www.nypl.org/blog/2016/11/08/what-eliza-hamilton-left-behind"
    },
    {
      "title": "Carve Your Own NYPL Pumpkin for Halloween",
      "date": "October 31, 2016",
      "timestamp": 1477886400,
      "text": "Happy Halloween! We carved a pumpkin worthy of the Library - and you can, too.",
      "url": "https://www.nypl.org/blog/2016/10/31/carve-your-own-nypl-pumpkin",
      "archive": "https://web.archive.org/web/20211031183741/https://www.nypl.org/blog/2016/10/31/carve-your-own-nypl-pumpkin",
      "oldestArchive": "https://web.archive.org/web/20211011154337/https://www.nypl.org/blog/2016/10/31/carve-your-own-nypl-pumpkin"
    },
    {
      "title": "It\u2019s Sweater Weather in Our Digital Collections",
      "date": "October 25, 2016",
      "timestamp": 1477368000,
      "text": "Leaves are changing color, the air smells crisp and clean, pumpkin spice everything is back in stores, and sweater weather is here at last! If you\u2019re looking for some fashion or knitting inspiration, the Digital Collections delivers some amazing designs from the 19th century.",
      "url": "https://www.nypl.org/blog/2016/10/25/its-sweater-weather-our-digital-collections",
      "archive": "https://web.archive.org/web/20190517104420/https://www.nypl.org/blog/2016/10/25/its-sweater-weather-our-digital-collections",
      "oldestArchive": "https://web.archive.org/web/20190517104420/https://www.nypl.org/blog/2016/10/25/its-sweater-weather-our-digital-collections"
    },
    {
      "title": "Quiz: Which Of These Are Not Stephen King Novels?",
      "date": "September 21, 2016",
      "timestamp": 1474430400,
      "text": "Stephen King has published over 50 novels since 1974. How well do you know his extensive list of books? See if you can spot the fake titles in this quiz.",
      "url": "https://www.nypl.org/blog/2016/09/21/quiz-stephen-king-novels",
      "archive": "https://web.archive.org/web/20211224222123/https://www.nypl.org/blog/2016/09/21/quiz-stephen-king-novels",
      "oldestArchive": "https://web.archive.org/web/20211224222122/https://www.nypl.org/blog/2016/09/21/quiz-stephen-king-novels"
    },
    {
      "title": "Celebrate Library Card Sign-Up Month with NYPL",
      "date": "September 13, 2016",
      "timestamp": 1473739200,
      "text": "September is Library Card Sign-Up Month! It couldn't be easier to get your free NYPL library card and take advantage of all the amazing resources it provides.",
      "url": "https://www.nypl.org/blog/2016/09/13/library-card-sign-up-month",
      "archive": "https://web.archive.org/web/20211224222615/https://www.nypl.org/blog/2016/09/13/library-card-sign-up-month",
      "oldestArchive": "https://web.archive.org/web/20211224222615/https://www.nypl.org/blog/2016/09/13/library-card-sign-up-month"
    },
    {
      "title": "A Bottle in a Cosmic Ocean: Listen to the Music of The Golden Record",
      "date": "August 31, 2016",
      "timestamp": 1472616000,
      "text": "On September 5, 1977, a tiny planet called Earth launched the Voyager 1 into the cosmos. To celebrate the anniversary of this hopeful project, here\u2019s a guide to all of the music included on The Golden Record.",
      "url": "https://www.nypl.org/blog/2016/08/31/listen-music-golden-record",
      "archive": "https://web.archive.org/web/20211225003653/https://www.nypl.org/blog/2016/08/31/listen-music-golden-record",
      "oldestArchive": "https://web.archive.org/web/20180820085411/https://www.nypl.org/blog/2016/08/31/listen-music-golden-record"
    },
    {
      "title": "5 Books for People Who Love the Internet",
      "date": "August 26, 2016",
      "timestamp": 1472184000,
      "text": "As an homage to 25 years of Internet life, I\u2019ve pulled a few books in which characters rely on the Internet, for better or worse, and two in Internet-less near-future worlds.",
      "url": "https://www.nypl.org/blog/2016/08/26/books-people-who-love-internet",
      "archive": "https://web.archive.org/web/20211224223623/https://www.nypl.org/blog/2016/08/26/books-people-who-love-internet",
      "oldestArchive": "https://web.archive.org/web/20211224223623/https://www.nypl.org/blog/2016/08/26/books-people-who-love-internet"
    },
    {
      "title": "1800s Astronomical Drawings vs. NASA Images",
      "date": "August 19, 2016",
      "timestamp": 1471579200,
      "text": "Comparing astrological drawings from our Digital Collections to NASA images\u2014how similar do you think they are?",
      "url": "https://www.nypl.org/blog/2016/08/19/1800s-astronomical-drawings",
      "archive": "https://web.archive.org/web/20211028153154/https://www.nypl.org/blog/2016/08/19/1800s-astronomical-drawings",
      "oldestArchive": "https://web.archive.org/web/20170115103135/https://www.nypl.org/blog/2016/08/19/1800s-astronomical-drawings"
    },
    {
      "title": "#CamerasAndDancers Visits the Library for the Performing Arts",
      "date": "August 16, 2016",
      "timestamp": 1471320000,
      "text": "With the social media initiative #CamerasAndDancers, Jacob Jonas seeks to encourage collaboration and exploration through the mediums of dance and photography, to help shine a new light on the world of dance.",
      "url": "https://www.nypl.org/blog/2016/08/16/camerasanddancers-visits-lpa",
      "archive": "https://web.archive.org/web/20210310221354/https://www.nypl.org/blog/2016/08/16/camerasanddancers-visits-lpa",
      "oldestArchive": "https://web.archive.org/web/20210310221354/https://www.nypl.org/blog/2016/08/16/camerasanddancers-visits-lpa"
    },
    {
      "title": "11 Harry Potter Quotes to Take You Back to Hogwarts",
      "date": "August 12, 2016",
      "timestamp": 1470974400,
      "text": "In the spirit of revisiting the magical world of Hogwarts, where I learned so many valuable lessons growing up and continue to find that feeling of home upon re-reading, I\u2019ve rounded up some of my favorite inspiring quotes from the Harry Potter series.",
      "url": "https://www.nypl.org/blog/2016/08/12/harry-potter-quotes-back-to-hogwarts",
      "archive": "https://web.archive.org/web/20201005161638/https://www.nypl.org/blog/2016/08/12/harry-potter-quotes-back-to-hogwarts",
      "oldestArchive": "https://web.archive.org/web/20201005161638/https://www.nypl.org/blog/2016/08/12/harry-potter-quotes-back-to-hogwarts"
    },
    {
      "title": "Catching 'Em All at NYPL with Pok\u00e9mon GO",
      "date": "July 8, 2016",
      "timestamp": 1467950400,
      "text": "Pok\u00e9mon GO brings childhood dreams to life while also showcasing some of the interesting and beautiful items around NYPL.",
      "url": "https://www.nypl.org/blog/2016/07/08/catching-em-all-nypl-pok%C3%A9mon-go",
      "archive": "https://web.archive.org/web/20211224224319/https://www.nypl.org/blog/2016/07/08/catching-em-all-nypl-pok%C3%A9mon-go",
      "oldestArchive": "https://web.archive.org/web/20211224224318/https://www.nypl.org/blog/2016/07/08/catching-em-all-nypl-pok%C3%A9mon-go"
    },
    {
      "title": "12 One Sentence Library Stories We Love",
      "date": "May 12, 2016",
      "timestamp": 1463025600,
      "text": "We've been asking New Yorkers to tell us in one sentence why they love the library or how it has impacted their life\u2014and 2,000 New Yorkers have already written sentences!",
      "url": "https://www.nypl.org/blog/2016/05/12/one-sentence-library-stories",
      "archive": "https://web.archive.org/web/20200410214834/https://www.nypl.org/blog/2016/05/12/one-sentence-library-stories",
      "oldestArchive": "https://web.archive.org/web/20160517110533/http://www.nypl.org:80/blog/2016/05/12/one-sentence-library-stories"
    },
    {
      "title": "Quiz: Can You Define These Obscure Words?",
      "date": "April 14, 2016",
      "timestamp": 1460606400,
      "text": "On April 14 in 1818, the first edition of Noah Webster's An American Dictionary of the English Language was published. To celebrate, we're challenging you to show off your knowledge of obscure definitions with this fun quiz.",
      "url": "https://www.nypl.org/blog/2016/04/14/define-obscure-words-quiz",
      "archive": "https://web.archive.org/web/20211224225104/https://www.nypl.org/blog/2016/04/14/define-obscure-words-quiz",
      "oldestArchive": "https://web.archive.org/web/20160419070656/http://www.nypl.org:80/blog/2016/04/14/define-obscure-words-quiz?"
    },
    {
      "title": "NYPL's 2016 Finalists for the NYC Neighborhood Library Awards",
      "date": "April 12, 2016",
      "timestamp": 1460433600,
      "text": "Four of our branches (Aguilar, Fort Washington, Inwood, and Morrisania) have been selected from hundreds of libraries in the city as finalists for the NYC Neighborhood Library Awards. The prizes, given out by a panel of judges, will be announced in June.",
      "url": "https://www.nypl.org/blog/2016/04/12/finalists-nyc-neighborhood-library-awards",
      "archive": "https://web.archive.org/web/20211224225217/https://www.nypl.org/blog/2016/04/12/finalists-nyc-neighborhood-library-awards",
      "oldestArchive": "https://web.archive.org/web/20160416071714/http://www.nypl.org:80/blog/2016/04/12/finalists-nyc-neighborhood-library-awards"
    },
    {
      "title": "Why We Love Beverly Cleary",
      "date": "April 12, 2016",
      "timestamp": 1460433600,
      "text": "Beverly Cleary turns 100 today, and to celebrate we asked some of our library staff to tell us why they love her. We picked a few of our favorite answers to share with you.",
      "url": "https://www.nypl.org/blog/2016/04/12/why-we-love-beverly-cleary",
      "archive": "https://web.archive.org/web/20211224225231/https://www.nypl.org/blog/2016/04/12/why-we-love-beverly-cleary",
      "oldestArchive": "https://web.archive.org/web/20160415164930/http://www.nypl.org:80/blog/2016/04/12/why-we-love-beverly-cleary"
    },
    {
      "title": "Celebrate National Library Week",
      "date": "April 11, 2016",
      "timestamp": 1460347200,
      "text": "It's National Library Week! The American Library Association encourages everyone to help spread the library love.",
      "url": "https://www.nypl.org/blog/2016/04/11/celebrate-national-library-week",
      "archive": "https://web.archive.org/web/20160416065209/http://www.nypl.org:80/blog/2016/04/11/celebrate-national-library-week",
      "oldestArchive": "https://web.archive.org/web/20160416065209/http://www.nypl.org:80/blog/2016/04/11/celebrate-national-library-week"
    },
    {
      "title": "Neil Gaiman on Women Writers Who Inspired Him",
      "date": "April 6, 2016",
      "timestamp": 1459915200,
      "text": "In the wake of Guy Talese saying he could name no women writers who had inspired him, author Neil Gaiman tweeted out a long list of women writers who have inspired his writing.",
      "url": "https://www.nypl.org/blog/2016/04/06/neil-gaiman-women-writers",
      "archive": "https://web.archive.org/web/20211224225329/https://www.nypl.org/blog/2016/04/06/neil-gaiman-women-writers",
      "oldestArchive": "https://web.archive.org/web/20160410113431/http://www.nypl.org:80/blog/2016/04/06/neil-gaiman-women-writers"
    },
    {
      "title": "NYPL Live Q&A with Marley Dias of #1000BlackGirlBooks",
      "date": "March 24, 2016",
      "timestamp": 1458792000,
      "text": "Join us Friday, March 25, at 1 PM Eastern for a live Twitter and Facebook chat with #1000BlackGirlBooks founder Marley Dias and the NYPL Recommends team.",
      "url": "https://www.nypl.org/blog/2016/03/24/live-qa-marley-dias-1000blackgirlbooks",
      "archive": "https://web.archive.org/web/20160818212029/http://www.nypl.org/blog/2016/03/24/live-qa-marley-dias-1000blackgirlbooks",
      "oldestArchive": "https://web.archive.org/web/20160326212319/http://www.nypl.org:80/blog/2016/03/24/live-qa-marley-dias-1000blackgirlbooks"
    },
    {
      "title": "#LiteraryMarchMadness 2016",
      "date": "March 16, 2016",
      "timestamp": 1458100800,
      "text": "Starting March 17, we'll be holding our Third Annual Literary March Madness! This is a bracket-style tournament like the NCAA March Madness basketball tournament, but with a literary twist: our competition pits famous authors against each other and the winner is decided by you! Sixteen authors will enter, only one can be crowned this year's crowd favorite.",
      "url": "https://www.nypl.org/blog/2016/03/16/literary-march-madness",
      "archive": "https://web.archive.org/web/20160825232945/http://www.nypl.org/blog/2016/03/16/literary-march-madness",
      "oldestArchive": "https://web.archive.org/web/20160319101107/http://www.nypl.org:80/blog/2016/03/16/literary-march-madness"
    },
    {
      "title": "In Memoriam: David Bowie's Top 100 Favorite Books",
      "date": "January 11, 2016",
      "timestamp": 1452488400,
      "text": "Though one of his songs is titled \"I Can't Read\", David Bowie was actually quite the voracious reader.",
      "url": "https://www.nypl.org/blog/2016/01/11/david-bowies-top-100-books",
      "archive": "https://web.archive.org/web/20211216222743/https://www.nypl.org/blog/2016/01/11/david-bowies-top-100-books",
      "oldestArchive": "https://web.archive.org/web/20160114065510/http://www.nypl.org:80/blog/2016/01/11/david-bowies-top-100-books"
    },
    {
      "title": "NYPL's Most Popular Check Outs of 2015",
      "date": "December 28, 2015",
      "timestamp": 1451278800,
      "text": "Over 20 million items are circulated through our network of 92 libraries each year, and among those items there are both expected front-runners and a few interesting surprises every year. We've compiled lists of the top books checked out systemwide and in The Bronx, Manhattan, and Staten Island in 2015.",
      "url": "https://www.nypl.org/blog/2015/12/28/nypls-most-popular-check-outs-2015",
      "archive": "https://web.archive.org/web/20211225003916/https://www.nypl.org/blog/2015/12/28/nypls-most-popular-check-outs-2015",
      "oldestArchive": "https://web.archive.org/web/20151231012208/http://www.nypl.org:80/blog/2015/12/28/nypls-most-popular-check-outs-2015"
    },
    {
      "title": "Library Stories: \"Destined to be a Librarian\"",
      "date": "December 18, 2015",
      "timestamp": 1450414800,
      "text": "\"Other kids played school and house and all of those things. I played library.\" - Dawn Collins (Zimmerer)",
      "url": "https://www.nypl.org/blog/2015/12/18/library-stories-destined-be-librarian",
      "archive": "https://web.archive.org/web/20210311033843/https://www.nypl.org/blog/2015/12/18/library-stories-destined-be-librarian",
      "oldestArchive": "https://web.archive.org/web/20151221032932/http://www.nypl.org:80/blog/2015/12/18/library-stories-destined-be-librarian?"
    },
    {
      "title": "Chocolate Lovers, Rejoice: National Brownie Day Is Here",
      "date": "December 8, 2015",
      "timestamp": 1449550800,
      "text": "If you were looking for an excuse to eat copious amounts of chocolate today, it\u2019s National Brownie Day! Find books at the library that will satisfy any brownie lover.",
      "url": "https://www.nypl.org/blog/2015/12/08/national-brownie-day",
      "archive": "https://web.archive.org/web/20161010225408/http://www.nypl.org/blog/2015/12/08/national-brownie-day",
      "oldestArchive": "https://web.archive.org/web/20151212111044/http://www.nypl.org:80/blog/2015/12/08/national-brownie-day"
    },
    {
      "title": "Make DIY Gift Tags with NYPL Digital Collections",
      "date": "December 2, 2015",
      "timestamp": 1449032400,
      "text": "Looking to add a colorful, personalized touch to your gifts this year? Look no further than our Digital Collections!",
      "url": "https://www.nypl.org/blog/2015/12/02/diy-gift-tags",
      "archive": "https://web.archive.org/web/20211224230222/https://www.nypl.org/blog/2015/12/02/diy-gift-tags",
      "oldestArchive": "https://web.archive.org/web/20151206085447/http://www.nypl.org:80/blog/2015/12/02/diy-gift-tags"
    },
    {
      "title": "#GivingTuesday: Dedicate a NYPL Bookplate",
      "date": "December 1, 2015",
      "timestamp": 1448946000,
      "text": "Want to give back for #GivingTuesday and honor someone in your life who loves books and learning? We\u2019ve got the perfect thing for you: until December 4, we\u2019re offering custom bookplates that will put your loved one\u2019s name into a library book!",
      "url": "https://www.nypl.org/blog/2015/12/01/giving-tuesday-bookplate",
      "archive": "https://web.archive.org/web/20211224230328/https://www.nypl.org/blog/2015/12/01/giving-tuesday-bookplate",
      "oldestArchive": "https://web.archive.org/web/20211224230326/https://www.nypl.org/blog/2015/12/01/giving-tuesday-bookplate"
    },
    {
      "title": "Announcing the Five Library Lions Honorees of 2015",
      "date": "October 26, 2015",
      "timestamp": 1445832000,
      "text": "On November 2, we will be recognizing five outstanding individuals for their achievements in the fields of art, culture, scholarship, and letters by naming them Library Lions at The New York Public Library's annual Library Lions gala.",
      "url": "https://www.nypl.org/blog/2015/10/07/library-lions-honorees",
      "archive": "https://web.archive.org/web/20210416030757/https://www.nypl.org/blog/2015/10/07/library-lions-honorees",
      "oldestArchive": "https://web.archive.org/web/20151011113659/http://www.nypl.org:80/blog/2015/10/07/library-lions-honorees"
    },
    {
      "title": "15 Writers on Writing",
      "date": "October 20, 2015",
      "timestamp": 1445313600,
      "text": "Whether you\u2019re writing the next War and Peace or just trying to think up the Next Great Tweet, here are a few writers\u2019 quotes on writing to get you through it:",
      "url": "https://www.nypl.org/blog/2015/10/20/15-writers-writing",
      "archive": "https://web.archive.org/web/20151231205845/http://www.nypl.org:80/blog/2015/10/20/15-writers-writing",
      "oldestArchive": "https://web.archive.org/web/20151023011220/http://www.nypl.org:80/blog/2015/10/20/15-writers-writing?"
    },
    {
      "title": "The Ellen DeGeneres Show Visits NYPL",
      "date": "October 14, 2015",
      "timestamp": 1444795200,
      "text": "Our Readers & Writers Shop in the Stephen A. Schwarzman Building recently welcomed a new employee for a day: Kevin the Cashier, from The Ellen DeGeneres Show!",
      "url": "https://www.nypl.org/blog/2015/10/14/ellen-degeneres-show",
      "archive": "https://web.archive.org/web/20211224231659/https://www.nypl.org/blog/2015/10/14/ellen-degeneres-show",
      "oldestArchive": "https://web.archive.org/web/20151022023952/http://www.nypl.org:80/blog/2015/10/14/ellen-degeneres-show"
    },
    {
      "title": "Show Us Your #LibraryCardSelfie!",
      "date": "September 17, 2015",
      "timestamp": 1442462400,
      "text": "Continuing our Library Card Sign-Up Month celebration this September, we\u2019re asking you to share your best #LibraryCardSelfie with us!",
      "url": "https://www.nypl.org/blog/2015/09/17/librarycardselfie",
      "archive": "https://web.archive.org/web/20211224231834/https://www.nypl.org/blog/2015/09/17/librarycardselfie",
      "oldestArchive": "https://web.archive.org/web/20150919061758/http://www.nypl.org:80/blog/2015/09/17/librarycardselfie"
    }
  ]
}